pytest_undine/__init__.py
pytest_undine/client.py
pytest_undine/fixtures.py
pytest_undine/query_logging.py
pytest_undine/websocket.py
undine/__init__.py
undine/apps.py
undine/calculation.py
undine/converters/__init__.py
undine/converters/definitions.py
undine/converters/impl/__init__.py
undine/converters/impl/convert_lookup_to_graphql_type.py
undine/converters/impl/convert_model_field_to_python_type.py
undine/converters/impl/convert_to_bad_lookups.py
undine/converters/impl/convert_to_default_value.py
undine/converters/impl/convert_to_description.py
undine/converters/impl/convert_to_entrypoint_ref.py
undine/converters/impl/convert_to_entrypoint_resolver.py
undine/converters/impl/convert_to_entrypoint_subscription.py
undine/converters/impl/convert_to_field_complexity.py
undine/converters/impl/convert_to_field_ref.py
undine/converters/impl/convert_to_field_resolver.py
undine/converters/impl/convert_to_filter_ref.py
undine/converters/impl/convert_to_filter_resolver.py
undine/converters/impl/convert_to_graphql_argument_map.py
undine/converters/impl/convert_to_graphql_type.py
undine/converters/impl/convert_to_input_ref.py
undine/converters/impl/convert_to_order_ref.py
undine/converters/impl/extend_expression.py
undine/converters/impl/is_field_nullable.py
undine/converters/impl/is_input_hidden.py
undine/converters/impl/is_input_only.py
undine/converters/impl/is_input_required.py
undine/converters/impl/is_many.py
undine/dataclasses.py
undine/dataloaders.py
undine/directives.py
undine/entrypoint.py
undine/exceptions.py
undine/execution.py
undine/filtering.py
undine/hooks.py
undine/http/__init__.py
undine/http/files.py
undine/http/urls.py
undine/http/utils.py
undine/http/views.py
undine/integrations/__init__.py
undine/integrations/channels.py
undine/integrations/debug_toolbar.py
undine/integrations/modeltranslation.py
undine/interface.py
undine/management/__init__.py
undine/management/commands/__init__.py
undine/management/commands/print_schema.py
undine/mutation.py
undine-0.2.2.dist-info/LICENSE
undine-0.2.2.dist-info/METADATA
undine-0.2.2.dist-info/WHEEL
undine-0.2.2.dist-info/entry_points.txt
undine-0.2.2.dist-info/RECORD
