Metadata-Version: 2.3
Name: undine
Version: 0.2.2
Summary: A GraphQL library for Django
License: MIT
Keywords: Django,GraphQL
Author: Matti Lamppu
Author-email: lamppu.matti.akseli@gmail.com
Requires-Python: >=3.11,<4
Classifier: Development Status :: 5 - Production/Stable
Classifier: Environment :: Web Environment
Classifier: Operating System :: OS Independent
Classifier: Intended Audience :: Developers
Classifier: Topic :: Utilities
Classifier: Topic :: Software Development :: Libraries
Classifier: Programming Language :: Python
Classifier: Programming Language :: Python :: 3
Classifier: Programming Language :: Python :: 3 :: Only
Classifier: Programming Language :: Python :: 3.11
Classifier: Programming Language :: Python :: 3.12
Classifier: Programming Language :: Python :: 3.13
Classifier: Programming Language :: Python :: 3.14
Classifier: Framework :: Django
Classifier: Framework :: Django :: 5.0
Classifier: Framework :: Django :: 5.1
Classifier: Framework :: Django :: 5.2
Classifier: Framework :: Django :: 6.0
Provides-Extra: channels
Provides-Extra: debug
Provides-Extra: image
Requires-Dist: channels (>=4.2.2) ; extra == "channels"
Requires-Dist: django (>=5.0)
Requires-Dist: django-debug-toolbar (>=5.2.0) ; extra == "debug"
Requires-Dist: django-settings-holder (>=0.3.0)
Requires-Dist: graphql-core (>=3.2.6)
Requires-Dist: pillow (>=11.2.1) ; extra == "image"
Requires-Dist: sqlparse (>=0.5.3)
Project-URL: Bug Tracker, https://github.com/MrThearMan/undine/issues
Project-URL: Documentation, https://mrthearman.github.io/undine
Project-URL: Homepage, https://mrthearman.github.io/undine
Project-URL: Repository, https://github.com/MrThearMan/undine
